{"Column_Names": ["Age", "Kilometers_Driven", "Fuel_Type", 
"Transmission", "Owner_Type", "Mileage", "Engine", "Power", 
"Seats", "Name_Ambassador", "Name_Audi", "Name_BMW", "Name_Bentley", 
"Name_Chevrolet", "Name_Datsun", "Name_Fiat", "Name_Force", "Name_Ford", 
"Name_Honda", "Name_Hyundai", "Name_ISUZU", "Name_Isuzu", "Name_Jaguar", 
"Name_Jeep", "Name_Lamborghini", "Name_Land", "Name_Mahindra", "Name_Maruti", 
"Name_Mercedes", "Name_Mini", "Name_Mitsubishi", "Name_Nissan", "Name_Porsche",
 "Name_Renault", "Name_Skoda", "Name_Smart", "Name_Tata", "Name_Toyota", 
 "Name_Volkswagen", "Name_Volvo", "Location_Ahmedabad", "Location_Bangalore", 
 "Location_Chennai", "Location_Coimbatore", "Location_Delhi", "Location_Hyderabad", 
 "Location_Jaipur", "Location_Kochi", "Location_Kolkata", "Location_Mumbai", 
 "Location_Pune"], 
 "Fuel_Type": {"Petrol": 0, "Diesel": 1, "CNG": 3, "LPG": 2, "Electric": 4}, 
 "Transmission": {"Manual": 0, "Automatic": 1}, 
 "Owner_Type": {"First": 1, "Second": 2, "Third": 3, "Fourth & Above": 4}}